autodistill_remote_clip/__init__.py
autodistill_remote_clip/remoteclip_model.py
autodistill_remote_clip-0.1.2.dist-info/LICENSE
autodistill_remote_clip-0.1.2.dist-info/METADATA
autodistill_remote_clip-0.1.2.dist-info/WHEEL
autodistill_remote_clip-0.1.2.dist-info/top_level.txt
autodistill_remote_clip-0.1.2.dist-info/RECORD
